{
  "001":{
    "code":"001",
    "name":"本店",
    "kana":"ホンテン",
    "hira":"ほんてん",
    "roma":"honten"
  },
  "002":{
    "code":"002",
    "name":"千手",
    "kana":"センジユ",
    "hira":"せんじゆ",
    "roma":"senjiyu"
  },
  "003":{
    "code":"003",
    "name":"台町",
    "kana":"ダイマチ",
    "hira":"だいまち",
    "roma":"daimachi"
  },
  "004":{
    "code":"004",
    "name":"新町",
    "kana":"アラマチ",
    "hira":"あらまち",
    "roma":"aramachi"
  },
  "005":{
    "code":"005",
    "name":"大島",
    "kana":"オオジマ",
    "hira":"おおじま",
    "roma":"oojima"
  },
  "006":{
    "code":"006",
    "name":"六日町",
    "kana":"ムイカマチ",
    "hira":"むいかまち",
    "roma":"muikamachi"
  },
  "007":{
    "code":"007",
    "name":"川崎",
    "kana":"カワサキ",
    "hira":"かわさき",
    "roma":"kawasaki"
  },
  "008":{
    "code":"008",
    "name":"宮内",
    "kana":"ミヤウチ",
    "hira":"みやうち",
    "roma":"miyauchi"
  },
  "009":{
    "code":"009",
    "name":"中島",
    "kana":"ナカジマ",
    "hira":"なかじま",
    "roma":"nakajima"
  },
  "010":{
    "code":"010",
    "name":"土合",
    "kana":"ドアイ",
    "hira":"どあい",
    "roma":"doai"
  },
  "011":{
    "code":"011",
    "name":"栃尾",
    "kana":"トチオ",
    "hira":"とちお",
    "roma":"tochio"
  },
  "013":{
    "code":"013",
    "name":"見附",
    "kana":"ミツケ",
    "hira":"みつけ",
    "roma":"mitsuke"
  },
  "014":{
    "code":"014",
    "name":"美園",
    "kana":"ミソノ",
    "hira":"みその",
    "roma":"misono"
  },
  "015":{
    "code":"015",
    "name":"江陽",
    "kana":"コウヨウ",
    "hira":"こうよう",
    "roma":"kouyou"
  },
  "016":{
    "code":"016",
    "name":"宝",
    "kana":"タカラ",
    "hira":"たから",
    "roma":"takara"
  },
  "017":{
    "code":"017",
    "name":"小千谷",
    "kana":"オヂヤ",
    "hira":"おぢや",
    "roma":"odiya"
  }
}
