{
  "001":{
    "code":"001",
    "name":"本店営業店",
    "kana":"ホンテン",
    "hira":"ほんてん",
    "roma":"honten"
  },
  "002":{
    "code":"002",
    "name":"駅前",
    "kana":"エキマエ",
    "hira":"えきまえ",
    "roma":"ekimae"
  },
  "003":{
    "code":"003",
    "name":"川原柳",
    "kana":"カワラヤナギ",
    "hira":"かわらやなぎ",
    "roma":"kawarayanagi"
  },
  "004":{
    "code":"004",
    "name":"大屋",
    "kana":"オオヤ",
    "hira":"おおや",
    "roma":"ooya"
  },
  "005":{
    "code":"005",
    "name":"丸子",
    "kana":"マルコ",
    "hira":"まるこ",
    "roma":"maruko"
  },
  "006":{
    "code":"006",
    "name":"常磐城",
    "kana":"トキワギ",
    "hira":"ときわぎ",
    "roma":"tokiwagi"
  },
  "007":{
    "code":"007",
    "name":"常田",
    "kana":"トキダ",
    "hira":"ときだ",
    "roma":"tokida"
  },
  "008":{
    "code":"008",
    "name":"塩田",
    "kana":"シオダ",
    "hira":"しおだ",
    "roma":"shioda"
  },
  "009":{
    "code":"009",
    "name":"とうみ",
    "kana":"トウミ",
    "hira":"とうみ",
    "roma":"toumi"
  },
  "010":{
    "code":"010",
    "name":"神科",
    "kana":"カミシナ",
    "hira":"かみしな",
    "roma":"kamishina"
  },
  "011":{
    "code":"011",
    "name":"城南",
    "kana":"ジヨウナン",
    "hira":"じようなん",
    "roma":"jiyounan"
  },
  "012":{
    "code":"012",
    "name":"真田",
    "kana":"サナダ",
    "hira":"さなだ",
    "roma":"sanada"
  },
  "013":{
    "code":"013",
    "name":"川西",
    "kana":"カワニシ",
    "hira":"かわにし",
    "roma":"kawanishi"
  },
  "014":{
    "code":"014",
    "name":"よだくぼ",
    "kana":"ヨダクボ",
    "hira":"よだくぼ",
    "roma":"yodakubo"
  },
  "015":{
    "code":"015",
    "name":"原町",
    "kana":"ハラマチ",
    "hira":"はらまち",
    "roma":"haramachi"
  },
  "051":{
    "code":"051",
    "name":"小諸",
    "kana":"コモロ",
    "hira":"こもろ",
    "roma":"komoro"
  },
  "052":{
    "code":"052",
    "name":"岩村田",
    "kana":"イワムラダ",
    "hira":"いわむらだ",
    "roma":"iwamurada"
  },
  "053":{
    "code":"053",
    "name":"野沢",
    "kana":"ノザワ",
    "hira":"のざわ",
    "roma":"nozawa"
  },
  "054":{
    "code":"054",
    "name":"御代田",
    "kana":"ミヨタ",
    "hira":"みよた",
    "roma":"miyota"
  },
  "055":{
    "code":"055",
    "name":"中込原",
    "kana":"ナカゴミハラ",
    "hira":"なかごみはら",
    "roma":"nakagomihara"
  },
  "056":{
    "code":"056",
    "name":"軽井沢",
    "kana":"カルイザワ",
    "hira":"かるいざわ",
    "roma":"karuizawa"
  },
  "057":{
    "code":"057",
    "name":"臼田",
    "kana":"ウスダ",
    "hira":"うすだ",
    "roma":"usuda"
  },
  "058":{
    "code":"058",
    "name":"和田森",
    "kana":"ワダモリ",
    "hira":"わだもり",
    "roma":"wadamori"
  }
}
