{
  "001":{
    "code":"001",
    "name":"東群馬営業部",
    "kana":"ヒガシグンマ",
    "hira":"ひがしぐんま",
    "roma":"higashigumma"
  },
  "002":{
    "code":"002",
    "name":"尾島",
    "kana":"オジマ",
    "hira":"おじま",
    "roma":"ojima"
  },
  "003":{
    "code":"003",
    "name":"太田宝泉",
    "kana":"オオタホウセン",
    "hira":"おおたほうせん",
    "roma":"ootahousen"
  },
  "004":{
    "code":"004",
    "name":"新田",
    "kana":"ニツタ",
    "hira":"につた",
    "roma":"nitsuta"
  },
  "005":{
    "code":"005",
    "name":"高林",
    "kana":"タカバヤシ",
    "hira":"たかばやし",
    "roma":"takabayashi"
  },
  "006":{
    "code":"006",
    "name":"伊勢崎",
    "kana":"イセサキ",
    "hira":"いせさき",
    "roma":"isesaki"
  },
  "011":{
    "code":"011",
    "name":"館林",
    "kana":"タテバヤシ",
    "hira":"たてばやし",
    "roma":"tatebayashi"
  },
  "013":{
    "code":"013",
    "name":"藪塚",
    "kana":"ヤブヅカ",
    "hira":"やぶづか",
    "roma":"yabuduka"
  },
  "021":{
    "code":"021",
    "name":"中之条",
    "kana":"ナカノジヨウ",
    "hira":"なかのじよう",
    "roma":"nakanojiyou"
  },
  "022":{
    "code":"022",
    "name":"草津温泉",
    "kana":"クサツオンセン",
    "hira":"くさつおんせん",
    "roma":"kusatsuonsen"
  },
  "023":{
    "code":"023",
    "name":"長野原",
    "kana":"ナガノハラ",
    "hira":"ながのはら",
    "roma":"naganohara"
  },
  "024":{
    "code":"024",
    "name":"嬬恋",
    "kana":"ツマゴイ",
    "hira":"つまごい",
    "roma":"tsumagoi"
  },
  "026":{
    "code":"026",
    "name":"原町",
    "kana":"ハラマチ",
    "hira":"はらまち",
    "roma":"haramachi"
  },
  "027":{
    "code":"027",
    "name":"北軽井沢",
    "kana":"キタカルイサワ",
    "hira":"きたかるいさわ",
    "roma":"kitakaruisawa"
  },
  "031":{
    "code":"031",
    "name":"渋川中央営業部",
    "kana":"シブカワチユウオウ",
    "hira":"しぶかわちゆうおう",
    "roma":"shibukawachiyuuou"
  },
  "032":{
    "code":"032",
    "name":"伊香保",
    "kana":"イカホ",
    "hira":"いかほ",
    "roma":"ikaho"
  },
  "033":{
    "code":"033",
    "name":"吉岡",
    "kana":"ヨシオカ",
    "hira":"よしおか",
    "roma":"yoshioka"
  },
  "034":{
    "code":"034",
    "name":"沼田",
    "kana":"ヌマタ",
    "hira":"ぬまた",
    "roma":"numata"
  },
  "035":{
    "code":"035",
    "name":"前橋",
    "kana":"マエバシ",
    "hira":"まえばし",
    "roma":"maebashi"
  },
  "037":{
    "code":"037",
    "name":"子持",
    "kana":"コモチ",
    "hira":"こもち",
    "roma":"komochi"
  },
  "039":{
    "code":"039",
    "name":"赤城",
    "kana":"アカギ",
    "hira":"あかぎ",
    "roma":"akagi"
  },
  "040":{
    "code":"040",
    "name":"前橋北",
    "kana":"マエバシキタ",
    "hira":"まえばしきた",
    "roma":"maebashikita"
  },
  "041":{
    "code":"041",
    "name":"大間々",
    "kana":"オオママ",
    "hira":"おおまま",
    "roma":"oomama"
  },
  "051":{
    "code":"051",
    "name":"本店",
    "kana":"ホンテン",
    "hira":"ほんてん",
    "roma":"honten"
  },
  "052":{
    "code":"052",
    "name":"箕郷",
    "kana":"ミサト",
    "hira":"みさと",
    "roma":"misato"
  },
  "053":{
    "code":"053",
    "name":"沖",
    "kana":"オキ",
    "hira":"おき",
    "roma":"oki"
  },
  "054":{
    "code":"054",
    "name":"群南",
    "kana":"グンナン",
    "hira":"ぐんなん",
    "roma":"gunnan"
  },
  "055":{
    "code":"055",
    "name":"総社",
    "kana":"ソウジヤ",
    "hira":"そうじや",
    "roma":"soujiya"
  },
  "056":{
    "code":"056",
    "name":"倉渕",
    "kana":"クラブチ",
    "hira":"くらぶち",
    "roma":"kurabuchi"
  },
  "057":{
    "code":"057",
    "name":"群馬町",
    "kana":"グンママチ",
    "hira":"ぐんままち",
    "roma":"gummamachi"
  },
  "061":{
    "code":"061",
    "name":"新町",
    "kana":"シンマチ",
    "hira":"しんまち",
    "roma":"shimmachi"
  },
  "062":{
    "code":"062",
    "name":"藤岡",
    "kana":"フジオカ",
    "hira":"ふじおか",
    "roma":"fujioka"
  },
  "064":{
    "code":"064",
    "name":"吉井",
    "kana":"ヨシイ",
    "hira":"よしい",
    "roma":"yoshii"
  },
  "065":{
    "code":"065",
    "name":"鬼石",
    "kana":"オニシ",
    "hira":"おにし",
    "roma":"onishi"
  },
  "067":{
    "code":"067",
    "name":"玉村",
    "kana":"タマムラ",
    "hira":"たまむら",
    "roma":"tamamura"
  }
}
