{
  "001":{
    "code":"001",
    "name":"本店",
    "kana":"ホンテン",
    "hira":"ほんてん",
    "roma":"honten"
  },
  "002":{
    "code":"002",
    "name":"青海",
    "kana":"オウミ",
    "hira":"おうみ",
    "roma":"oumi"
  },
  "003":{
    "code":"003",
    "name":"上越",
    "kana":"ジヨウエツ",
    "hira":"じようえつ",
    "roma":"jiyouetsu"
  },
  "004":{
    "code":"004",
    "name":"梶屋敷",
    "kana":"カジヤシキ",
    "hira":"かじやしき",
    "roma":"kajiyashiki"
  },
  "005":{
    "code":"005",
    "name":"能生",
    "kana":"ノウ",
    "hira":"のう",
    "roma":"nou"
  },
  "006":{
    "code":"006",
    "name":"本町",
    "kana":"ホンチヨウ",
    "hira":"ほんちよう",
    "roma":"honchiyou"
  }
}
