{
  "001":{
    "code":"001",
    "name":"本店",
    "kana":"ホンテン",
    "hira":"ほんてん",
    "roma":"honten"
  },
  "004":{
    "code":"004",
    "name":"大野",
    "kana":"オオノ",
    "hira":"おおの",
    "roma":"oono"
  },
  "007":{
    "code":"007",
    "name":"稲荷",
    "kana":"イナリ",
    "hira":"いなり",
    "roma":"inari"
  },
  "008":{
    "code":"008",
    "name":"佐々",
    "kana":"サザ",
    "hira":"さざ",
    "roma":"saza"
  },
  "009":{
    "code":"009",
    "name":"波佐見",
    "kana":"ハサミ",
    "hira":"はさみ",
    "roma":"hasami"
  },
  "011":{
    "code":"011",
    "name":"平戸",
    "kana":"ヒラド",
    "hira":"ひらど",
    "roma":"hirado"
  },
  "013":{
    "code":"013",
    "name":"早岐",
    "kana":"ハイキ",
    "hira":"はいき",
    "roma":"haiki"
  },
  "014":{
    "code":"014",
    "name":"松浦",
    "kana":"マツウラ",
    "hira":"まつうら",
    "roma":"matsuura"
  },
  "015":{
    "code":"015",
    "name":"大村",
    "kana":"オオムラ",
    "hira":"おおむら",
    "roma":"oomura"
  }
}
