{
  "001":{
    "code":"001",
    "name":"本店",
    "kana":"ホンテン",
    "hira":"ほんてん",
    "roma":"honten"
  },
  "002":{
    "code":"002",
    "name":"花巻",
    "kana":"ハナマキ",
    "hira":"はなまき",
    "roma":"hanamaki"
  },
  "006":{
    "code":"006",
    "name":"矢沢",
    "kana":"ヤサワ",
    "hira":"やさわ",
    "roma":"yasawa"
  },
  "009":{
    "code":"009",
    "name":"宮野目",
    "kana":"ミヤノメ",
    "hira":"みやのめ",
    "roma":"miyanome"
  },
  "010":{
    "code":"010",
    "name":"湯本",
    "kana":"ユモト",
    "hira":"ゆもと",
    "roma":"yumoto"
  },
  "015":{
    "code":"015",
    "name":"湯口",
    "kana":"ユグチ",
    "hira":"ゆぐち",
    "roma":"yuguchi"
  },
  "019":{
    "code":"019",
    "name":"太田",
    "kana":"オオタ",
    "hira":"おおた",
    "roma":"oota"
  },
  "020":{
    "code":"020",
    "name":"笹間",
    "kana":"ササマ",
    "hira":"ささま",
    "roma":"sasama"
  },
  "022":{
    "code":"022",
    "name":"石鳥谷",
    "kana":"イシドリヤ",
    "hira":"いしどりや",
    "roma":"ishidoriya"
  },
  "024":{
    "code":"024",
    "name":"石鳥谷東",
    "kana":"イシドリヤヒガシ",
    "hira":"いしどりやひがし",
    "roma":"ishidoriyahigashi"
  },
  "027":{
    "code":"027",
    "name":"大迫町",
    "kana":"オオハサママチ",
    "hira":"おおはさままち",
    "roma":"oohasamamachi"
  },
  "028":{
    "code":"028",
    "name":"東和町",
    "kana":"トウワチヨウ",
    "hira":"とうわちよう",
    "roma":"touwachiyou"
  },
  "032":{
    "code":"032",
    "name":"北上",
    "kana":"キタカミ",
    "hira":"きたかみ",
    "roma":"kitakami"
  },
  "033":{
    "code":"033",
    "name":"みなみ",
    "kana":"ミナミ",
    "hira":"みなみ",
    "roma":"minami"
  },
  "034":{
    "code":"034",
    "name":"さくら",
    "kana":"サクラ",
    "hira":"さくら",
    "roma":"sakura"
  },
  "035":{
    "code":"035",
    "name":"二子",
    "kana":"フタゴ",
    "hira":"ふたご",
    "roma":"futago"
  },
  "036":{
    "code":"036",
    "name":"和賀町",
    "kana":"ワガマチ",
    "hira":"わがまち",
    "roma":"wagamachi"
  },
  "037":{
    "code":"037",
    "name":"江釣子",
    "kana":"エヅリコ",
    "hira":"えづりこ",
    "roma":"eduriko"
  },
  "038":{
    "code":"038",
    "name":"岩崎",
    "kana":"イワサキ",
    "hira":"いわさき",
    "roma":"iwasaki"
  },
  "039":{
    "code":"039",
    "name":"横川目",
    "kana":"ヨコカワメ",
    "hira":"よこかわめ",
    "roma":"yokokawame"
  },
  "040":{
    "code":"040",
    "name":"湯田",
    "kana":"ユダ",
    "hira":"ゆだ",
    "roma":"yuda"
  },
  "041":{
    "code":"041",
    "name":"沢内",
    "kana":"サワウチ",
    "hira":"さわうち",
    "roma":"sawauchi"
  },
  "042":{
    "code":"042",
    "name":"遠野",
    "kana":"トオノ",
    "hira":"とおの",
    "roma":"toono"
  },
  "044":{
    "code":"044",
    "name":"上郷",
    "kana":"カミゴウ",
    "hira":"かみごう",
    "roma":"kamigou"
  },
  "045":{
    "code":"045",
    "name":"宮守",
    "kana":"ミヤモリ",
    "hira":"みやもり",
    "roma":"miyamori"
  },
  "046":{
    "code":"046",
    "name":"大槌",
    "kana":"オオヅチ",
    "hira":"おおづち",
    "roma":"ooduchi"
  },
  "047":{
    "code":"047",
    "name":"鵜住居",
    "kana":"ウノスマイ",
    "hira":"うのすまい",
    "roma":"unosumai"
  },
  "048":{
    "code":"048",
    "name":"釜石",
    "kana":"カマイシ",
    "hira":"かまいし",
    "roma":"kamaishi"
  }
}
