{
  "001":{
    "code":"001",
    "name":"本店",
    "kana":"ホンテン",
    "hira":"ほんてん",
    "roma":"honten"
  },
  "002":{
    "code":"002",
    "name":"北山形",
    "kana":"キタヤマガタ",
    "hira":"きたやまがた",
    "roma":"kitayamagata"
  },
  "003":{
    "code":"003",
    "name":"小白川",
    "kana":"コジラカワ",
    "hira":"こじらかわ",
    "roma":"kojirakawa"
  },
  "004":{
    "code":"004",
    "name":"下条",
    "kana":"シモジヨウ",
    "hira":"しもじよう",
    "roma":"shimojiyou"
  },
  "005":{
    "code":"005",
    "name":"上町",
    "kana":"ウワマチ",
    "hira":"うわまち",
    "roma":"uwamachi"
  },
  "006":{
    "code":"006",
    "name":"美畑",
    "kana":"ミハタ",
    "hira":"みはた",
    "roma":"mihata"
  }
}
