{
  "002":{
    "code":"002",
    "name":"明和北",
    "kana":"メイワキタ",
    "hira":"めいわきた",
    "roma":"meiwakita"
  },
  "003":{
    "code":"003",
    "name":"明和南",
    "kana":"メイワミナミ",
    "hira":"めいわみなみ",
    "roma":"meiwaminami"
  },
  "009":{
    "code":"009",
    "name":"多気",
    "kana":"タキ",
    "hira":"たき",
    "roma":"taki"
  },
  "013":{
    "code":"013",
    "name":"多気勢和",
    "kana":"タキセイワ",
    "hira":"たきせいわ",
    "roma":"takiseiwa"
  },
  "019":{
    "code":"019",
    "name":"大台",
    "kana":"オオダイ",
    "hira":"おおだい",
    "roma":"oodai"
  },
  "020":{
    "code":"020",
    "name":"大台宮川",
    "kana":"オオダイミヤガワ",
    "hira":"おおだいみやがわ",
    "roma":"oodaimiyagawa"
  },
  "100":{
    "code":"100",
    "name":"本店",
    "kana":"ホンテン",
    "hira":"ほんてん",
    "roma":"honten"
  }
}
