{
  "001":{
    "code":"001",
    "name":"北条富田",
    "kana":"ホウジヨウトミタ",
    "hira":"ほうじようとみた",
    "roma":"houjiyoutomita"
  },
  "004":{
    "code":"004",
    "name":"善防",
    "kana":"ゼンボウ",
    "hira":"ぜんぼう",
    "roma":"zembou"
  },
  "006":{
    "code":"006",
    "name":"加西",
    "kana":"カサイ",
    "hira":"かさい",
    "roma":"kasai"
  },
  "007":{
    "code":"007",
    "name":"多加野",
    "kana":"タカノ",
    "hira":"たかの",
    "roma":"takano"
  },
  "009":{
    "code":"009",
    "name":"在田",
    "kana":"アリタ",
    "hira":"ありた",
    "roma":"arita"
  },
  "011":{
    "code":"011",
    "name":"三木市久留美",
    "kana":"ミキシクルミ",
    "hira":"みきしくるみ",
    "roma":"mikishikurumi"
  },
  "012":{
    "code":"012",
    "name":"志染",
    "kana":"シジミ",
    "hira":"しじみ",
    "roma":"shijimi"
  },
  "013":{
    "code":"013",
    "name":"広野",
    "kana":"ヒロノ",
    "hira":"ひろの",
    "roma":"hirono"
  },
  "015":{
    "code":"015",
    "name":"豊地",
    "kana":"トヨチ",
    "hira":"とよち",
    "roma":"toyochi"
  },
  "016":{
    "code":"016",
    "name":"緑が丘",
    "kana":"ミドリガオカ",
    "hira":"みどりがおか",
    "roma":"midorigaoka"
  },
  "021":{
    "code":"021",
    "name":"小野中央",
    "kana":"オノチユウオウ",
    "hira":"おのちゆうおう",
    "roma":"onochiyuuou"
  },
  "022":{
    "code":"022",
    "name":"河合",
    "kana":"カワイ",
    "hira":"かわい",
    "roma":"kawai"
  },
  "025":{
    "code":"025",
    "name":"小野南",
    "kana":"オノミナミ",
    "hira":"おのみなみ",
    "roma":"onominami"
  },
  "027":{
    "code":"027",
    "name":"下東条",
    "kana":"シモトウジヨウ",
    "hira":"しもとうじよう",
    "roma":"shimotoujiyou"
  },
  "100":{
    "code":"100",
    "name":"本店",
    "kana":"ホンテン",
    "hira":"ほんてん",
    "roma":"honten"
  }
}
