{
  "010":{
    "code":"010",
    "name":"洲本",
    "kana":"スモト",
    "hira":"すもと",
    "roma":"sumoto"
  },
  "020":{
    "code":"020",
    "name":"津名",
    "kana":"ツナ",
    "hira":"つな",
    "roma":"tsuna"
  },
  "025":{
    "code":"025",
    "name":"生穂",
    "kana":"イクホ",
    "hira":"いくほ",
    "roma":"ikuho"
  },
  "030":{
    "code":"030",
    "name":"東浦淡路",
    "kana":"ヒガシウラアワジ",
    "hira":"ひがしうらあわじ",
    "roma":"higashiuraawaji"
  },
  "033":{
    "code":"033",
    "name":"岩屋",
    "kana":"イワヤ",
    "hira":"いわや",
    "roma":"iwaya"
  },
  "050":{
    "code":"050",
    "name":"北淡",
    "kana":"ホクダン",
    "hira":"ほくだん",
    "roma":"hokudan"
  },
  "056":{
    "code":"056",
    "name":"育波",
    "kana":"イクハ",
    "hira":"いくは",
    "roma":"ikuha"
  },
  "060":{
    "code":"060",
    "name":"一宮",
    "kana":"イチノミヤ",
    "hira":"いちのみや",
    "roma":"ichinomiya"
  },
  "070":{
    "code":"070",
    "name":"鮎原",
    "kana":"アイハラ",
    "hira":"あいはら",
    "roma":"aihara"
  },
  "071":{
    "code":"071",
    "name":"都志",
    "kana":"ツシ",
    "hira":"つし",
    "roma":"tsushi"
  },
  "072":{
    "code":"072",
    "name":"五色",
    "kana":"ゴシキ",
    "hira":"ごしき",
    "roma":"goshiki"
  },
  "100":{
    "code":"100",
    "name":"本店",
    "kana":"ホンテン",
    "hira":"ほんてん",
    "roma":"honten"
  }
}
